easytranscribe/__init__.py
easytranscribe/_version.py
easytranscribe/cli.py
easytranscribe/speech_to_text.py
easytranscribe/transcription_logger.py
easytranscribe/view_logs.py
easytranscribe-0.1.2.dist-info/licenses/LICENSE
easytranscribe-0.1.2.dist-info/METADATA
easytranscribe-0.1.2.dist-info/WHEEL
easytranscribe-0.1.2.dist-info/entry_points.txt
easytranscribe-0.1.2.dist-info/top_level.txt
easytranscribe-0.1.2.dist-info/RECORD
