Metadata-Version: 2.4
Name: easytranscribe
Version: 0.1.2
Summary: Easy speech-to-text transcription from audio files or live microphone input using Whisper.
Home-page: https://github.com/akhshyganesh/easytranscribe
Author: akhshyganesh
Author-email: 
License: MIT License
Project-URL: Homepage, https://github.com/akhshyganesh/easytranscribe
Project-URL: Bug Reports, https://github.com/akhshyganesh/easytranscribe/issues
Project-URL: Source Code, https://github.com/akhshyganesh/easytranscribe
Keywords: speech-to-text,whisper,transcription,audio,ai
Classifier: Development Status :: 4 - Beta
Classifier: Intended Audience :: Developers
Classifier: Topic :: Multimedia :: Sound/Audio :: Speech
Classifier: Topic :: Scientific/Engineering :: Artificial Intelligence
Classifier: License :: OSI Approved :: MIT License
Classifier: Programming Language :: Python :: 3
Classifier: Programming Language :: Python :: 3.8
Classifier: Programming Language :: Python :: 3.9
Classifier: Programming Language :: Python :: 3.10
Classifier: Programming Language :: Python :: 3.11
Classifier: Programming Language :: Python :: 3.12
Classifier: Operating System :: OS Independent
Requires-Python: >=3.8
License-File: LICENSE
Requires-Dist: openai-whisper>=20240930
Requires-Dist: sounddevice>=0.4.6
Requires-Dist: numpy<2.3,>=1.21.0
Provides-Extra: dev
Requires-Dist: pytest>=6.0; extra == "dev"
Requires-Dist: pytest-cov; extra == "dev"
Requires-Dist: black; extra == "dev"
Requires-Dist: flake8; extra == "dev"
Requires-Dist: mypy; extra == "dev"
Dynamic: home-page
Dynamic: license-file
Dynamic: requires-python
